pit/envelope/v1/envelope_pb2.py
pit/events/v1/events_pb2.py
pit_proto-0.2.3.dist-info/METADATA
pit_proto-0.2.3.dist-info/WHEEL
pit_proto-0.2.3.dist-info/top_level.txt
pit_proto-0.2.3.dist-info/RECORD
