Metadata-Version: 2.4
Name: pit-proto
Version: 0.2.3
Requires-Python: >=3.10
Requires-Dist: protobuf>=5.29.0
